coolmaker/__init__.py
coolmaker-1.4.1.dist-info/METADATA
coolmaker-1.4.1.dist-info/WHEEL
coolmaker-1.4.1.dist-info/top_level.txt
coolmaker-1.4.1.dist-info/RECORD
