Metadata-Version: 2.1
Name: coolmaker
Version: 1.4.1
Summary: 为教育目的而制作启蒙动画与游戏模块。主要提供继承自Turtle类的Sprite类。作者：酷哥创客。网址：http://www.coolguymaker.com
Home-page: http://www.coolguymaker.com
Author: coolmaker
Author-email: wangyf@coolguymaker.com
License: MIT
Keywords: creative game pygame turtle animation sprite
Platform: UNKNOWN
Requires-Dist: pillow (>=2.7.0)
Requires-Dist: numpy
